[
  {
    "id": "project-1",
    "name": "A股市场情绪监测",
    "description": "监测A股市场相关新闻、论坛讨论中的市场情绪变化",
    "status": "active",
    "targetType": "index",
    "targetIds": [],
    "keywords": {
      "core": [
        "A股",
        "沪深",
        "大盘",
        "指数"
      ],
      "extended": [
        "沪深300",
        "上证",
        "深证",
        "两市"
      ],
      "exclude": [
        "广告"
      ]
    },
    "sourceTypes": [
      "news",
      "forums",
      "social"
    ],
    "sourceWeights": [
      {
        "sourceType": "news",
        "weight": 0.8,
        "enabled": true
      },
      {
        "sourceType": "broker",
        "weight": 1,
        "enabled": false
      },
      {
        "sourceType": "forums",
        "weight": 0.5,
        "enabled": true
      },
      {
        "sourceType": "social",
        "weight": 0.4,
        "enabled": true
      },
      {
        "sourceType": "app",
        "weight": 0.6,
        "enabled": false
      }
    ],
    "temperatureThreshold": 70,
    "alertThreshold": 80,
    "outputCycle": "hourly",
    "sentimentThreshold": -0.5,
    "riskThreshold": "high",
    "hitCount": 0,
    "createdAt": "2026-01-15T08:00:00Z",
    "updatedAt": "2026-03-19T10:00:00Z"
  },
  {
    "id": "project-2",
    "name": "新能源产业链追踪",
    "description": "跟踪新能源汽车、光伏、锂电池等产业链的舆情动态",
    "status": "active",
    "targetType": "sector",
    "targetIds": [
      "industry-new-energy"
    ],
    "keywords": {
      "core": [
        "新能源",
        "比亚迪",
        "宁德时代",
        "光伏",
        "锂电池"
      ],
      "extended": [
        "电动汽车",
        "储能",
        "风电",
        "碳中和",
        "双碳"
      ],
      "exclude": [
        "招聘"
      ]
    },
    "sourceTypes": [
      "news",
      "broker",
      "forums"
    ],
    "sourceWeights": [
      {
        "sourceType": "news",
        "weight": 0.8,
        "enabled": true
      },
      {
        "sourceType": "broker",
        "weight": 1,
        "enabled": true
      },
      {
        "sourceType": "forums",
        "weight": 0.5,
        "enabled": true
      },
      {
        "sourceType": "social",
        "weight": 0.4,
        "enabled": false
      },
      {
        "sourceType": "app",
        "weight": 0.6,
        "enabled": false
      }
    ],
    "temperatureThreshold": 70,
    "alertThreshold": 80,
    "outputCycle": "hourly",
    "sentimentThreshold": -0.3,
    "riskThreshold": "medium",
    "hitCount": 0,
    "createdAt": "2026-02-01T08:00:00Z",
    "updatedAt": "2026-03-18T14:30:00Z"
  },
  {
    "id": "project-3",
    "name": "央行货币政策监测",
    "description": "实时追踪央行政策动态、利率变化、流动性投放等",
    "status": "active",
    "targetType": "concept",
    "targetIds": [],
    "keywords": {
      "core": [
        "央行",
        "货币政策",
        "降息",
        "降准",
        "LPR"
      ],
      "extended": [
        "利率",
        "流动性",
        "再贷款",
        "存款准备金",
        "公开市场"
      ],
      "exclude": []
    },
    "sourceTypes": [
      "news",
      "broker"
    ],
    "sourceWeights": [
      {
        "sourceType": "news",
        "weight": 0.8,
        "enabled": true
      },
      {
        "sourceType": "broker",
        "weight": 1,
        "enabled": true
      },
      {
        "sourceType": "forums",
        "weight": 0.5,
        "enabled": false
      },
      {
        "sourceType": "social",
        "weight": 0.4,
        "enabled": false
      },
      {
        "sourceType": "app",
        "weight": 0.6,
        "enabled": false
      }
    ],
    "temperatureThreshold": 65,
    "alertThreshold": 75,
    "outputCycle": "realtime",
    "sentimentThreshold": -0.6,
    "riskThreshold": "high",
    "hitCount": 0,
    "createdAt": "2026-01-20T08:00:00Z",
    "updatedAt": "2026-03-19T09:00:00Z"
  },
  {
    "id": "project-1780883906321",
    "name": "AI科技情绪监测",
    "status": "active",
    "targetType": "sector",
    "targetIds": [
      "industry-ai",
      "industry-semiconductor"
    ],
    "keywords": {
      "core": [
        "AI",
        "内存",
        "存储",
        "GPU",
        "CPU",
        "CPO",
        "光模块",
        "PCB",
        "大模型",
        "Agent",
        "MLCC"
      ],
      "extended": [
        "科创",
        "算力",
        "国产替代"
      ],
      "exclude": []
    },
    "sourceTypes": [
      "news",
      "broker",
      "forums",
      "social",
      "app"
    ],
    "sourceWeights": [
      {
        "sourceType": "news",
        "weight": 0.8,
        "enabled": true
      },
      {
        "sourceType": "broker",
        "weight": 1,
        "enabled": true
      },
      {
        "sourceType": "forums",
        "weight": 0.5,
        "enabled": true
      },
      {
        "sourceType": "social",
        "weight": 0.5,
        "enabled": true
      },
      {
        "sourceType": "app",
        "weight": 0.2,
        "enabled": true
      }
    ],
    "temperatureThreshold": 70,
    "alertThreshold": 80,
    "outputCycle": "daily",
    "hitCount": 0,
    "createdAt": "2026-06-08T01:58:26.321Z",
    "updatedAt": "2026-06-08T02:01:41.363Z",
    "description": "ai科技板块的监测方案"
  },
  {
    "id": "project-1780884059341",
    "name": "有色金属监测",
    "description": "有色金属板块的舆情监测",
    "status": "active",
    "targetType": "sector",
    "targetIds": [
      "industry-metals"
    ],
    "keywords": {
      "core": [
        "有色金属",
        "小金属",
        "能源金属",
        "战略金属",
        "稀有金属",
        "铝",
        "铬",
        "钨"
      ],
      "extended": [],
      "exclude": []
    },
    "sourceTypes": [
      "news",
      "broker",
      "forums",
      "social",
      "app"
    ],
    "sourceWeights": [
      {
        "sourceType": "news",
        "weight": 0.8,
        "enabled": true
      },
      {
        "sourceType": "broker",
        "weight": 1,
        "enabled": true
      },
      {
        "sourceType": "forums",
        "weight": 0.5,
        "enabled": true
      },
      {
        "sourceType": "social",
        "weight": 0.4,
        "enabled": true
      },
      {
        "sourceType": "app",
        "weight": 0.2,
        "enabled": true
      }
    ],
    "temperatureThreshold": 70,
    "alertThreshold": 80,
    "outputCycle": "daily",
    "hitCount": 0,
    "createdAt": "2026-06-08T02:00:59.341Z",
    "updatedAt": "2026-06-08T02:00:59.341Z"
  }
]